fastapi_autowire/__init__.py
fastapi_autowire/py.typed
fastapi_autowire/types.py
fastapi_autowire/core/__init__.py
fastapi_autowire/core/app_context.py
fastapi_autowire/core/dependencies.py
fastapi_autowire/core/lifespan.py
fastapi_autowire/core/logger.py
fastapi_autowire/core/registry.py
fastapi_autowire/core/resolver.py
fastapi_autowire-0.1.1.dist-info/METADATA
fastapi_autowire-0.1.1.dist-info/WHEEL
fastapi_autowire-0.1.1.dist-info/licenses/LICENSE
fastapi_autowire-0.1.1.dist-info/RECORD
