Metadata-Version: 2.4
Name: fastapi-autowire
Version: 0.1.1
Summary: Spring-like Dependency Injection and Autowiring for FastAPI
Author-email: Tuo Nome <tua.email@example.com>
License: MIT License
License-File: LICENSE
Keywords: autowire,dependency-injection,di,fastapi,ioc,spring
Classifier: Development Status :: 4 - Beta
Classifier: Framework :: FastAPI
Classifier: Intended Audience :: Developers
Classifier: Programming Language :: Python :: 3
Classifier: Programming Language :: Python :: 3.9
Classifier: Programming Language :: Python :: 3.10
Classifier: Programming Language :: Python :: 3.11
Classifier: Programming Language :: Python :: 3.12
Classifier: Topic :: Software Development :: Libraries :: Python Modules
Classifier: Typing :: Typed
Requires-Python: >=3.9
Requires-Dist: fastapi>=0.100.0
Requires-Dist: typing-extensions>=4.0.0; python_version < '3.10'
